[{"title": "Toshiba N300 PRO 18TB Large-Sized Business NAS (up to 24 bays) 3.5-Inch Internal Hard Drive - Up to 300 TB/year Workload Rate CMR SATA 6 GB/s 7200 RPM 512 MB Cache - HDWG51JXZSTB", "total_reviews": "103  ", "price": "334.99", "image_url": "https://m.media-amazon.com/images/I/71lU8en-E0L._AC_UY218_.jpg"}, {"title": "Crucial X10 Pro 1TB Portable SSD - Up to 2100MB/s Read, 2000MB/s Write -Water and dust Resistant, PC and Mac, with Mylio Photos+ Offer - USB 3.2 External Solid State Drive - CT1000X10PROSSD902", "total_reviews": "538  ", "price": "104.99", "image_url": "https://m.media-amazon.com/images/I/81QnLlCBxfL._AC_UY218_.jpg"}, {"title": "Toshiba Canvio Basics 2TB Portable External Hard Drive USB 3.0, Black - HDTB520XK3AA", "total_reviews": "75,930  ", "price": "64.61", "image_url": "https://m.media-amazon.com/images/I/81HElDSuH0L._AC_UY218_.jpg"}, {"title": "Seagate Portable 5TB External Hard Drive HDD \u2013 USB 3.0 for PC, Mac, PS4, & Xbox - 1-Year Rescue Service (STGX5000400), Black", "total_reviews": "244,152  ", "price": "119.99", "image_url": "https://m.media-amazon.com/images/I/81o5zJ+FcPL._AC_UY218_.jpg"}, {"title": "Western Digital 2TB Elements Portable HDD, External Hard Drive, USB 3.0 for PC & Mac, Plug and Play Ready - WDBU6Y0020BBK-WESN", "total_reviews": "268,673  ", "price": "72.99", "image_url": "https://m.media-amazon.com/images/I/41fJs1xw6bL._AC_UY218_.jpg"}, {"title": "Western Digital WD 1TB My Passport Portable External Hard Drive with backup software and password protection, Black - WDBYVG0010BBK-WESN", "total_reviews": "100,210  ", "price": "54.99", "image_url": "https://m.media-amazon.com/images/I/510+J06fz0L._AC_UY218_.jpg"}, {"title": "SanDisk 1TB Portable SSD - Up to 800MB/s, USB-C, USB 3.2 Gen 2, Updated Firmware - External Solid State Drive - SDSSDE30-1T00-G26", "total_reviews": "10,221  ", "price": "84.99", "image_url": "https://m.media-amazon.com/images/I/71bBCTIvIIL._AC_UY218_.jpg"}, {"title": "Western Digital 18TB Elements Desktop External Hard Drive USB 3.0 for plug-and-play storage - Western DigitalBWLG0180HBK-NESN", "total_reviews": "24,676  ", "price": "289.99", "image_url": "https://m.media-amazon.com/images/I/71MDGnNGWYL._AC_UY218_.jpg"}, {"title": "SanDisk 1TB Extreme Portable SSD - Up to 1050MB/s, USB-C, USB 3.2 Gen 2, IP65 Water and Dust Resistance, Updated Firmware - External Solid State Drive - SDSSDE61-1T00-G25", "total_reviews": "57,998  ", "price": "85.00", "image_url": "https://m.media-amazon.com/images/I/61zuR3UMnWL._AC_UY218_.jpg"}, {"title": "WD_BLACK 5TB P10 Game Drive - Portable External Hard Drive HDD, Compatible with Playstation, Xbox, PC, & Mac - WDBA3A0050BBK-WESN", "total_reviews": "44,383  ", "price": "139.95", "image_url": "https://m.media-amazon.com/images/I/91ekP94ki4L._AC_UY218_.jpg"}, {"title": "Toshiba Canvio Flex 2TB Portable External Hard Drive USB-C USB 3.0, Silver for PC, Mac, & Tablet - HDTX120XSCAA", "total_reviews": "6,762  ", "price": "80.99", "image_url": "https://m.media-amazon.com/images/I/71-C7VUBGwL._AC_UY218_.jpg"}, {"title": "Crucial X9 Pro for Mac 1TB Portable SSD - Up to 1050MB/s Read and Write - Mac Ready, with Mylio Photos+ Offer - USB 3.2 External Solid State Drive - CT1000X9PROMACSSD9B02", "total_reviews": "1,430  ", "price": "99.99", "image_url": "https://m.media-amazon.com/images/I/61Az-YSbGtL._AC_UY218_.jpg"}, {"title": "Seagate One Touch, 2TB, Password activated hardware encryption, portable external hard drive, portable external hard drive, PC, Notebook & Mac, USB 3.0, Black (STKY2000400)", "total_reviews": "21,250  ", "price": "78.79", "image_url": "https://m.media-amazon.com/images/I/71VDyTlZCwL._AC_UY218_.jpg"}, {"title": "Western Digital 8TB WD Purple Surveillance Internal Hard Drive HDD - SATA 6 Gb/s, 256 MB Cache, 3.5\" - WD85PURZ", "total_reviews": "13,214  ", "price": "209.99", "image_url": "https://m.media-amazon.com/images/I/71r36xP5wbL._AC_UY218_.jpg"}, {"title": "Crucial X6 2TB Portable SSD - Up to 800MB/s - PC and Mac - USB 3.2 USB-C External Solid State Drive - CT2000X6SSD9, Black", "total_reviews": "2,934  ", "price": "114.99", "image_url": "https://m.media-amazon.com/images/I/51S83kOP3YL._AC_UY218_.jpg"}, {"title": "Western Digital 10TB WD Red Plus NAS Internal Hard Drive HDD - 7200 RPM, SATA 6 Gb/s, CMR, 256 MB Cache, 3.5\" - WD101EFBX", "total_reviews": "8,815  ", "price": "199.99", "image_url": "https://m.media-amazon.com/images/I/71598zUypjL._AC_UY218_.jpg"}, {"title": "LaCie Rugged Mini 4TB External Hard Drive Portable HDD - USB 3.0 Compatible, Drop/Shock/Dust/Rain Resistant Shuttle Drive for Mac and PC", "total_reviews": "18,978  ", "price": "137.99", "image_url": "https://m.media-amazon.com/images/I/81h+P-kLOnL._AC_UY218_.jpg"}, {"title": "Western Digital 8TB WD Blue PC Internal Hard Drive HDD - 5640 RPM, SATA 6 Gb/s, 256 MB Cache, 3.5\" - WD80EAAZ", "total_reviews": "54,243  ", "price": "129.99", "image_url": "https://m.media-amazon.com/images/I/71if+ezy99L._AC_UY218_.jpg"}, {"title": "LaCie Rugged Mini 4TB External Hard Drive Portable HDD - USB 3.0 Compatible, Drop/Shock/Dust/Rain Resistant Shuttle Drive for Mac and PC", "total_reviews": "18,978  ", "price": "137.99", "image_url": "https://m.media-amazon.com/images/I/81h+P-kLOnL._AC_UY218_.jpg"}, {"title": "Seagate Exos 7E8 4TB 512n SATA 128MB Cache 3.5-Inch Enterprise Hard Drive (ST4000NM0035), Mechanical Hard Disk", "total_reviews": "140  ", "price": "88.72", "image_url": "https://m.media-amazon.com/images/I/91pqZtyFQYL._AC_UY218_.jpg"}, {"title": "Toshiba X300 16TB Performance & Gaming 3.5-Inch Internal Hard Drive \u2013 CMR SATA 6 GB/s 7200 RPM 512 MB Cache - HDWR31GXZSTA", "total_reviews": "1,375  ", "price": "314.99", "image_url": "https://m.media-amazon.com/images/I/71Rq2n2RtAL._AC_UY218_.jpg"}, {"title": "Seagate Skyhawk 6TB Video Internal Hard Drive HDD \u2013 3.5 Inch SATA 6Gb/s 256MB Cache for DVR NVR Security Camera System with in-House Rescue Services (ST6000VXZ09/009)", "total_reviews": "5,662  ", "price": "129.99", "image_url": "https://m.media-amazon.com/images/I/71ncqWCGTPL._AC_UY218_.jpg"}]