[{"title": "Patriot Signature DDR3 RAM 8GB (1X8GB) 1600MHz CL11 UDIMM Desktop Memory Module - PSD38G16002", "total_reviews": "2,949  ", "price": "14.99", "image_url": "https://m.media-amazon.com/images/I/812Qd5srW9L._AC_UY218_.jpg", "scrape_date": "2024-03-09"}, {"title": "v-Color DDR4 32GB (2 x 16GB) 2666MHz (PC4-21300) Dual Rank Server Memory Ram Module Upgrade ECC DIMM 1.2V CL19 2Rx8 (TE416G26D819K-VKC)", "total_reviews": "188  ", "price": "139.99", "image_url": "https://m.media-amazon.com/images/I/7151NjeIn-L._AC_UY218_.jpg", "scrape_date": "2024-03-09"}, {"title": "Silicon Power Value Gaming DDR4 RAM 16GB (2x8GB) 3200MHz (PC4 25600) CL16 1.35V Desktop Memory Module with Heatsink Camouflage Grey SP016GXLZU320BDAJ5", "total_reviews": "6,006  ", "price": "34.97", "image_url": "https://m.media-amazon.com/images/I/71hqLlS98ZL._AC_UY218_.jpg", "scrape_date": "2024-03-09"}, {"title": "Silicon Power DDR3 16GB (2 x 8GB) 1600MHz (PC3 12800) 240-Pin CL11 1.35V / 1.5V Unbuffered UDIMM PC Computer Desktop Memory Module Ram Upgrade", "total_reviews": "3,408  ", "price": "19.99", "image_url": "https://m.media-amazon.com/images/I/71hbRsn4DZL._AC_UY218_.jpg", "scrape_date": "2024-03-09"}, {"title": "G.SKILL Trident Z5 RGB Series (Intel XMP 3.0) DDR5 RAM 64GB (2x32GB) 6400MT/s CL32-39-39-102 1.40V Desktop Computer Memory UDIMM - Matte Black (F5-6400J3239G32GX2-TZ5RK)", "total_reviews": "922  ", "price": "", "image_url": "https://m.media-amazon.com/images/I/51c+p6RY+AL._AC_UY218_.jpg", "scrape_date": "2024-03-09"}, {"title": "10Pcs DDR Memory RAM Module Case Plastic Box Packaging Container Clamshell Antistatic Tray for DDR2, DDR3 and DDR4 Long DIMM Desktop Memory RAM Module", "total_reviews": "33  ", "price": "8.99", "image_url": "https://m.media-amazon.com/images/I/61F45l1jvtL._AC_UY218_.jpg", "scrape_date": "2024-03-09"}, {"title": "10 pcs DDR Memory Desktop RAM Module Case,Plastic Box Packaging Container Clamshell Memory Module,Antistatic Tray for DDR2, DDR3 and DDR4", "total_reviews": "105  ", "price": "9.99", "image_url": "https://m.media-amazon.com/images/I/513JJh2FqOL._AC_UY218_.jpg", "scrape_date": "2024-03-09"}, {"title": "Samsung 4GB DDR4 SODIMM RAM Module 3200MHz 1Rx16 PC4-3200AA 260-Pin SDRAM Laptop Memory M471A5244CB0-CWE", "total_reviews": "466  ", "price": "7.95", "image_url": "https://m.media-amazon.com/images/I/51hK3Hu4f-L._AC_UY218_.jpg", "scrape_date": "2024-03-09"}, {"title": "Samsung 16GB DDR4 3200MHz SODIMM PC4-25600 CL22 2Rx8 1.2V 260-Pin SO-DIMM Laptop Notebook RAM Memory Module M471A2K43DB1-CWE", "total_reviews": "273  ", "price": "46.70", "image_url": "https://m.media-amazon.com/images/I/81bkhaiG32L._AC_UY218_.jpg", "scrape_date": "2024-03-09"}, {"title": "Silicon Power DDR5 32GB (2x16GB) Zenith 6000MHz (PC5-48000) 288-pin CL30 1.35V UDIMM Desktop Memory Module RAM SP032GXLWU60AFDE Black", "total_reviews": "43  ", "price": "97.97", "image_url": "https://m.media-amazon.com/images/I/71rub9gdBpL._AC_UY218_.jpg", "scrape_date": "2024-03-09"}, {"title": "A-Tech 16GB DDR5 4800MHz PC5-38400 CL40 SODIMM 1.1V Non-ECC Unbuffered SO-DIMM 262-Pin Laptop RAM Memory Upgrade Module", "total_reviews": "61  ", "price": "45.46", "image_url": "https://m.media-amazon.com/images/I/71Z9RJCSG1L._AC_UY218_.jpg", "scrape_date": "2024-03-09"}, {"title": "16GB DDR4 3200MHz PC4-25600 CL22 1.2V 288-Pin Non-ECC UDIMM Desktop RAM Memory Module", "total_reviews": "67  ", "price": "31.49", "image_url": "https://m.media-amazon.com/images/I/51aCUwfF75L._AC_UY218_.jpg", "scrape_date": "2024-03-09"}, {"title": "TEAMGROUP T-Force Delta RGB DDR4 64GB (2x32GB) 3600MHz (PC4-28800) CL18 Desktop Gaming Memory Module Ram Black - TF3D464G3600HC18JDC01", "total_reviews": "78  ", "price": "", "image_url": "https://m.media-amazon.com/images/I/71yyY+Y29WL._AC_UY218_.jpg", "scrape_date": "2024-03-09"}, {"title": "TEAMGROUP T-Force Delta RGB DDR4 32GB (2x16GB) 3600MHz (PC4-28800) CL18 Desktop Gaming Memory Module Ram Black - TF3D432G3600HC18JDC01", "total_reviews": "4,137  ", "price": "", "image_url": "https://m.media-amazon.com/images/I/71yyY+Y29WL._AC_UY218_.jpg", "scrape_date": "2024-03-09"}, {"title": "Timetec 16GB KIT(2x8GB) DDR3L/DDR3 1600MHz(DDR3L-1600) PC3L-12800 Non-ECC Unbuffered 1.35V/1.5V CL11 2Rx8 Dual Rank 204 Pin SODIMM Laptop Notebook RAM", "total_reviews": "25,506  ", "price": "19.99", "image_url": "https://m.media-amazon.com/images/I/71tovgbX0zL._AC_UY218_.jpg", "scrape_date": "2024-03-09"}, {"title": "TEAMGROUP T-Create Expert Overclocking 10L DDR5 32GB Kit (2 x 16GB) 6000MHz (PC5-48000) CL30 Intel XMP 3.0 & AMD Expo Compatible Desktop Memory Module Ram Black - CTCED532G6000HC30DC01", "total_reviews": "295  ", "price": "", "image_url": "https://m.media-amazon.com/images/I/91Zx8tlgk8L._AC_UY218_.jpg", "scrape_date": "2024-03-09"}, {"title": "Timetec 8GB DDR4 2666MHz PC4-21300 Non-ECC Unbuffered 1.2V CL19 1Rx8 Single Rank 288 Pin UDIMM Desktop PC Computer Memory RAM Module Upgrade (8GB)", "total_reviews": "895  ", "price": "17.99", "image_url": "https://m.media-amazon.com/images/I/61WUNQJ3OsL._AC_UY218_.jpg", "scrape_date": "2024-03-09"}, {"title": "Silicon Power Hynix IC Compatible for Apple DDR3 DDR3L 16GB (2x8GB) RAM 1600MHz (PC3 12800) 204 pin CL11 1.35V Non ECC Unbuffered SODIMM Laptop Notebook Memory RAM Module Upgrade", "total_reviews": "3,449  ", "price": "19.89", "image_url": "https://m.media-amazon.com/images/I/61fdgvdk9AL._AC_UY218_.jpg", "scrape_date": "2024-03-09"}, {"title": "Patriot Viper Steel DDR4 RAM 16GB (1X16GB) 3200MHz CL16 UDIMM Desktop Gaming Memory Module - PVS416G320C6", "total_reviews": "11,767  ", "price": "37.99", "image_url": "https://m.media-amazon.com/images/I/81XNrcp5BKL._AC_UY218_.jpg", "scrape_date": "2024-03-09"}, {"title": "8GB DDR4 3200MHz PC4-25600 CL22 1.2V 288-Pin Non-ECC UDIMM Desktop RAM Memory Module", "total_reviews": "67  ", "price": "19.49", "image_url": "https://m.media-amazon.com/images/I/51CqaJiYPuL._AC_UY218_.jpg", "scrape_date": "2024-03-09"}, {"title": "Memory Signature DDR3 16GB (2 x 8GB CL11 PC3-12800 (1600MHz) CAS 11 DIMM Kit with Heatshield", "total_reviews": "2,017  ", "price": "29.99", "image_url": "https://m.media-amazon.com/images/I/81hOBtiHDpL._AC_UY218_.jpg", "scrape_date": "2024-03-09"}, {"title": "A-Tech 16GB DDR4 2666MHz PC4-21300 (PC4-2666V) CL19 SODIMM 1.2V 260-Pin Non-ECC SO-DIMM Laptop Notebook RAM Memory Module", "total_reviews": "1,561  ", "price": "38.00", "image_url": "https://m.media-amazon.com/images/I/81pxLw3d-7L._AC_UY218_.jpg", "scrape_date": "2024-03-09"}, {"title": "A-Tech 16GB (2x8GB) DDR3/DDR3L 1600MHz PC3L-12800 (PC3-12800) CL11 SODIMM 2Rx8 1.35V 204-Pin Non-ECC SO-DIMM Laptop, Notebook RAM Memory Modules", "total_reviews": "11,599  ", "price": "32.74", "image_url": "https://m.media-amazon.com/images/I/81vqthn7EML._AC_UY218_.jpg", "scrape_date": "2024-03-09"}, {"title": "Silicon Power DDR4 16GB (2x8GB) Zenith 3200MHz (PC4 25600) 288-pin CL16 1.35V UDIMM Desktop Memory Module RAM SP016GXLZU320BDC Metallic Grey", "total_reviews": "1,826  ", "price": "37.99", "image_url": "https://m.media-amazon.com/images/I/51kLzNeRdwL._AC_UY218_.jpg", "scrape_date": "2024-03-09"}, {"title": "Hynix 8GB PC4-21300 DDR4-2666MHz 288-Pin DIMM 1.2V Memory RAM Module HMA81GU6CJR8N-VK", "total_reviews": "136  ", "price": "21.98", "image_url": "https://m.media-amazon.com/images/I/51Kd0axK8IL._AC_UY218_.jpg", "scrape_date": "2024-03-09"}, {"title": "Samsung 32GB (1x32GB) DDR4 3200 MHz PC4-25600 SODIMM 2Rx8 CL22 1.2v 260-PIN Laptop Notebook Memory Module RAM Upgrade M471A4G43AB1-CWE M471A4G43CB1-CWE Adamanta", "total_reviews": "44  ", "price": "80.00", "image_url": "https://m.media-amazon.com/images/I/715RQ9q8EAL._AC_UY218_.jpg", "scrape_date": "2024-03-09"}, {"title": "Timetec 32GB KIT(2x16GB) DDR4 3200MHz (or 2933MHz or 2666MHz) PC4-25600 Non-ECC Unbuffered 1.2V CL22 2Rx8 Dual Rank 260 Pin SODIMM Laptop Notebook PC Computer Memory RAM Module Upgrade", "total_reviews": "1,712  ", "price": "54.99", "image_url": "https://m.media-amazon.com/images/I/718f84SxgmL._AC_UY218_.jpg", "scrape_date": "2024-03-09"}, {"title": "TEAMGROUP T-Force Delta RGB DDR5 Ram 32GB (2x16GB) 6000MHz PC5-48000 CL30 Intel XMP 3.0 & AMD Expo Compatible Desktop Memory Module Ram White - FF4D532G6000HC30DC01", "total_reviews": "1,147  ", "price": "", "image_url": "https://m.media-amazon.com/images/I/81JEfdUVCTL._AC_UY218_.jpg", "scrape_date": "2024-03-09"}, {"title": "A-Tech 32GB (2x16GB) DDR4 3200 MHz SODIMM PC4-25600 (PC4-3200AA) CL22 Non-ECC Laptop RAM Memory Modules", "total_reviews": "719  ", "price": "88.97", "image_url": "https://m.media-amazon.com/images/I/81rI3PTtXsL._AC_UY218_.jpg", "scrape_date": "2024-03-09"}, {"title": "Patriot Signature Line DDR4 Memory 16GB (1 x 16GB) 3200MHz (2 Rank Double-sided module) - PSD416G32002", "total_reviews": "68  ", "price": "33.99", "image_url": "https://m.media-amazon.com/images/I/81pvsZ6G2eL._AC_UY218_.jpg", "scrape_date": "2024-03-09"}, {"title": "Patriot Signature Premium DDR4 16GB (1x16GB) 2666MHz (PC4-21300) UDIMM W/Heatshield", "total_reviews": "38  ", "price": "29.99", "image_url": "https://m.media-amazon.com/images/I/81g-3riIUeL._AC_UY218_.jpg", "scrape_date": "2024-03-09"}, {"title": "32GB (2X16GB) DDR4-2666 PC4-21300 ECC SODIMM Compatible with Synology D4ECSO-2666-16G Memory Upgrade Module by NEMIX RAM", "total_reviews": "144  ", "price": "96.88", "image_url": "https://m.media-amazon.com/images/I/81wQTzcLhDL._AC_UY218_.jpg", "scrape_date": "2024-03-09"}, {"title": "A-Tech 16GB (4x4GB) DDR3 1600MHz PC3-12800 CL11 DIMM 240-Pin Non-ECC UDIMM Desktop RAM Memory Modules", "total_reviews": "5,522  ", "price": "50.38", "image_url": "https://m.media-amazon.com/images/I/81cW03MFaLL._AC_UY218_.jpg", "scrape_date": "2024-03-09"}, {"title": "Timetec 16GB KIT(2x8GB) DDR3 1600MHz (DDR3-1600) PC3-12800 (PC3-12800U) Non-ECC Unbuffered 1.5V CL11 2Rx8 Dual Rank 240 Pin UDIMM Desktop PC Computer Memory RAM(SDRAM) Module Upgrade", "total_reviews": "9,006  ", "price": "19.99", "image_url": "https://m.media-amazon.com/images/I/71fPJs5GIvL._AC_UY218_.jpg", "scrape_date": "2024-03-09"}, {"title": "Timetec Pinnacle Konduit 16GB KIT(2x8GB) DDR4 3200MHz PC4-25600 CL16-18-18-38 XMP2.0 Overclocking 1.35V Compatible for AMD and Intel Desktop Gaming PC Memory Module RAM - Black", "total_reviews": "290  ", "price": "44.99", "image_url": "https://m.media-amazon.com/images/I/71fLEvD7j3L._AC_UY218_.jpg", "scrape_date": "2024-03-09"}, {"title": "A-Tech 16GB (2x8GB) DDR4 3200 MHz UDIMM PC4-25600 (PC4-3200AA) CL22 DIMM Non-ECC Desktop RAM Memory Modules", "total_reviews": "242  ", "price": "47.96", "image_url": "https://m.media-amazon.com/images/I/81trF3cDjzL._AC_UY218_.jpg", "scrape_date": "2024-03-09"}, {"title": "A-Tech 16GB DDR4 2400 MHz SODIMM PC4-19200 (PC4-2400T) CL17 2Rx8 Non-ECC Laptop RAM Memory Module", "total_reviews": "1,558  ", "price": "42.68", "image_url": "https://m.media-amazon.com/images/I/81kw1BEKPqL._AC_UY218_.jpg", "scrape_date": "2024-03-09"}, {"title": "1866MHZ DDR3 RAM 16GB(2 * 8GB) 1.5V(PC3-14900) CL10 UDIMM PC Computer Desktop Memory Module Ram Upgrade Unbuffered Non-ECC Desktop Computer Memory", "total_reviews": "2  ", "price": "22.99", "image_url": "https://m.media-amazon.com/images/I/61maKzQ3-lL._AC_UY218_.jpg", "scrape_date": "2024-03-09"}, {"title": "A-Tech 32GB DDR4 2666 MHz UDIMM PC4-21300 (PC4-2666V) CL19 DIMM 2Rx8 Non-ECC Desktop RAM Memory Module", "total_reviews": "749  ", "price": "74.41", "image_url": "https://m.media-amazon.com/images/I/71OZGE52z4L._AC_UY218_.jpg", "scrape_date": "2024-03-09"}, {"title": "Patriot Memory Signature Premium DDR4 16GB (2x8GB) 2666MHz (PC4-21300) UDIMM Kit with Heatshield PSP416G2666KH1", "total_reviews": "560  ", "price": "39.99", "image_url": "https://m.media-amazon.com/images/I/81e+68VClAL._AC_UY218_.jpg", "scrape_date": "2024-03-09"}, {"title": "Patriot Signature DDR3 RAM 4GB (1X4GB) 1333MHz CL9 UDIMM Desktop Memory Module - PSD34G13332", "total_reviews": "1,034  ", "price": "10.99", "image_url": "https://m.media-amazon.com/images/I/812Qd5srW9L._AC_UY218_.jpg", "scrape_date": "2024-03-09"}, {"title": "Patriot Memory Signature Premium DDR4 8GB (1x8GB) 2666MHz (PC4-21300) UDIMM with Heatshield PSP48G266681H1", "total_reviews": "1,401  ", "price": "19.99", "image_url": "https://m.media-amazon.com/images/I/81UN8XaAvEL._AC_UY218_.jpg", "scrape_date": "2024-03-09"}, {"title": "TEAMGROUP Elite DDR4 32GB Kit (2 x 16GB) 3200MHz (2933MHz or 2666MHz) PC4-25600 CL22 Unbuffered Non-ECC 1.2V SODIMM 260-Pin Laptop Notebook PC Computer Memory Module Ram Upgrade - TED432G3200C22DC-S01", "total_reviews": "2,551  ", "price": "", "image_url": "https://m.media-amazon.com/images/I/812oSOwR5+L._AC_UY218_.jpg", "scrape_date": "2024-03-09"}, {"title": "A-Tech 32GB (2x16GB) DDR4 2133 MHz UDIMM PC4-17000 (PC4-2133P) CL15 DIMM 2Rx8 Non-ECC Desktop RAM Memory Modules", "total_reviews": "801  ", "price": "105.40", "image_url": "https://m.media-amazon.com/images/I/81l0tZX0dBL._AC_UY218_.jpg", "scrape_date": "2024-03-09"}, {"title": "32GB DDR4 3200MHz PC4-25600 1.2V 2Rx8 260-Pin SODIMM Laptop RAM Memory Module M471A4G43AB1-CWE\u2026", "total_reviews": "318  ", "price": "80.00", "image_url": "https://m.media-amazon.com/images/I/619qX0kTqEL._AC_UY218_.jpg", "scrape_date": "2024-03-09"}, {"title": "DUOMEIQI Ram DDR4 32GB 3200MHz (2x16GB) Kit PC4 25600 Sodimm Laptop Ram CL22 1.2V Non-ECC Unbuffered (PC4-25600S) 260 Pin Notebook Memory Ram Module Upgrade", "total_reviews": "221  ", "price": "60.98", "image_url": "https://m.media-amazon.com/images/I/71LZrCVSQOL._AC_UY218_.jpg", "scrape_date": "2024-03-09"}, {"title": "OWC 16.0GB (4 x 4GB) 1333MHz DDR3 SO-DIMM PC3-10600 204Pin SO-DIMM CL9 Memory RAM Upgrade Module for iMac and PC Laptops (OWC1333DDR3S16S)", "total_reviews": "1,690  ", "price": "39.99", "image_url": "https://m.media-amazon.com/images/I/71Ha2eIi44L._AC_UY218_.jpg", "scrape_date": "2024-03-09"}, {"title": "Timetec 32GB KIT(2x16GB) DDR4 2133MHz PC4-17000 Non-ECC Unbuffered 1.2V CL15 2Rx8 Dual Rank 288 Pin UDIMM Desktop PC Computer Memory RAM Module Upgrade (32GB KIT(2x16GB))", "total_reviews": "660  ", "price": "57.99", "image_url": "https://m.media-amazon.com/images/I/71jg+dNsHYL._AC_UY218_.jpg", "scrape_date": "2024-03-09"}, {"title": "16GB DDR5 4800MHz SODIMM PC5-38400 CL40 1Rx8 1.1V SO-DIMM 262-Pin Laptop Notebook RAM Memory Module M425R2GA3BB0-CQK", "total_reviews": "26  ", "price": "49.39", "image_url": "https://m.media-amazon.com/images/I/719WN3ljEML._AC_UY218_.jpg", "scrape_date": "2024-03-09"}, {"title": "Timetec 32GB KIT(2x16GB) DDR4 2666MHz PC4-21300 Non-ECC Unbuffered 1.2V CL19 2Rx8 Dual Rank 288 Pin UDIMM Desktop Memory RAM Module Upgrade (32GB KIT(2x16GB))", "total_reviews": "895  ", "price": "53.99", "image_url": "https://m.media-amazon.com/images/I/71H121okOlL._AC_UY218_.jpg", "scrape_date": "2024-03-09"}, {"title": "Patriot Memory Signature Premium DDR4 32GB (2x16GB) 3200MHz (PC4-25600) UDIMM Kit W/HEATSHIELD", "total_reviews": "644  ", "price": "65.99", "image_url": "https://m.media-amazon.com/images/I/81e+68VClAL._AC_UY218_.jpg", "scrape_date": "2024-03-09"}, {"title": "Patriot PSD38G16002H Signature 8GB DDR3 CL11 PC3-12800 1600MHz DIMM with Heatshield", "total_reviews": "829  ", "price": "17.99", "image_url": "https://m.media-amazon.com/images/I/71yc8rkFTmL._AC_UY218_.jpg", "scrape_date": "2024-03-09"}, {"title": "Crucial RAM 16GB DDR4 3200MHz CL22 (or 2933MHz or 2666MHz) Laptop Memory CT16G4SFRA32A", "total_reviews": "41,409  ", "price": "36.99", "image_url": "https://m.media-amazon.com/images/I/71oz85Vv6mL._AC_UY218_.jpg", "scrape_date": "2024-03-09"}, {"title": "Timetec 32GB KIT(2x16GB) DDR4 SODIMM for Intel NUC KIT/Mini PC/HTPC/NUC Board 2133MHz PC4-17000 Non-ECC Unbuffered 1.2V CL15 Dual Rank 260 Pin Computer Memory Ram Module Upgrade (32GB KIT(2x16GB))", "total_reviews": "171  ", "price": "54.99", "image_url": "https://m.media-amazon.com/images/I/71TwzX7v8GL._AC_UY218_.jpg", "scrape_date": "2024-03-09"}, {"title": "Timetec 32GB KIT(2x16GB) DDR4 2400MHz PC4-19200 Non-ECC Unbuffered 1.2V CL17 2Rx8 Dual Rank 260 Pin SODIMM Laptop Notebook PC Computer Memory RAM Module Upgrade (32GB KIT(2x16GB))", "total_reviews": "4,654  ", "price": "54.99", "image_url": "https://m.media-amazon.com/images/I/71mCZc9H-RL._AC_UY218_.jpg", "scrape_date": "2024-03-09"}, {"title": "A-Tech 16GB (2x8GB) RAM for Apple iMac Late 2015 27 inch Retina 5K | DDR3L 1866MHz / 1867MHz PC3L-14900 1.35V 204-Pin SODIMM Memory Upgrade Kit", "total_reviews": "361  ", "price": "39.88", "image_url": "https://m.media-amazon.com/images/I/91-zBOrgqXL._AC_UY218_.jpg", "scrape_date": "2024-03-09"}, {"title": "Samsung 32GB (2x16GB) DDR5 4800MHz PC5-38400 UDIMM Unbuffered Non-ECC 1Rx8 CL40 1.1v Desktop PC Computer Memory Module Upgrade RAM M323R2GA3BB0-CQK Adamanta", "total_reviews": "8  ", "price": "120.00", "image_url": "https://m.media-amazon.com/images/I/61BH9fkNLLL._AC_UY218_.jpg", "scrape_date": "2024-03-09"}, {"title": "Samsung 16GB (1x16GB) DDR5 4800MHz PC5-38400 SODIMM M425R2GA3BB0-CQK 1Rx8 CL40 1.1v Notebook Laptop RAM Memory Module Upgrade Adamanta", "total_reviews": "15  ", "price": "59.00", "image_url": "https://m.media-amazon.com/images/I/71AEIk7kzIL._AC_UY218_.jpg", "scrape_date": "2024-03-09"}, {"title": "Samsung M471A2K43CB1-CRC 16GB DDR4 2400MHz Memory Module", "total_reviews": "103  ", "price": "33.01", "image_url": "https://m.media-amazon.com/images/I/616VsyQjtVL._AC_UY218_.jpg", "scrape_date": "2024-03-09"}, {"title": "16GB DDR4 3200MHz PC4-25600 CL22 SODIMM 1.2V 260-Pin Non-ECC SODIMM Laptop Notebook RAM Memory Module", "total_reviews": "79  ", "price": "31.49", "image_url": "https://m.media-amazon.com/images/I/51WbPcPCM2L._AC_UY218_.jpg", "scrape_date": "2024-03-09"}, {"title": "Timetec 8GB DDR3 1600MHz(DDR3-1600) PC3-12800 Non-ECC Unbuffered 1.5V CL11 2Rx8 Dual Rank 240 Pin UDIMM Desktop PC Computer Memory RAM Module Upgrade", "total_reviews": "9,006  ", "price": "11.99", "image_url": "https://m.media-amazon.com/images/I/71sS86AKYeL._AC_UY218_.jpg", "scrape_date": "2024-03-09"}, {"title": "Timetec 16GB KIT(2x8GB) DDR3 / DDR3L 1333MHz PC3-10600 Non-ECC Unbuffered 1.5V / 1.35V CL9 2Rx8 Dual Rank 240 Pin UDIMM PC Desktop Computer Memory RAM Module Upgrade (16GB KIT(2x8GB))", "total_reviews": "4,843  ", "price": "19.99", "image_url": "https://m.media-amazon.com/images/I/71QpXmdIoxL._AC_UY218_.jpg", "scrape_date": "2024-03-09"}, {"title": "Patriot Signature DDR4 RAM 8GB (1X8GB) 2400MHz CL17 SODIMM Laptop/Notebook Memory Module - PSD48G240081S", "total_reviews": "2,203  ", "price": "19.99", "image_url": "https://m.media-amazon.com/images/I/81eI5VA8U9L._AC_UY218_.jpg", "scrape_date": "2024-03-09"}, {"title": "Samsung 8GB DDR4 3200MHz SODIMM PC4-25600 CL22 1Rx8 1.2V 260-Pin SO-DIMM Laptop Notebook RAM Memory Module M471A1K43DB1-CWE", "total_reviews": "704  ", "price": "25.01", "image_url": "https://m.media-amazon.com/images/I/81PPnONPDxL._AC_UY218_.jpg", "scrape_date": "2024-03-09"}, {"title": "A-Tech 8GB Memory RAM for Dell Inspiron 15 3000 3543 - DDR3L 1600MHz PC3-12800 Non ECC SO-DIMM 2Rx8 1.35V - Single Laptop & Notebook Upgrade Module (Replacement for SNPN2M64C/8G)", "total_reviews": "1  ", "price": "19.99", "image_url": "https://m.media-amazon.com/images/I/81IR16Cd0vL._AC_UY218_.jpg", "scrape_date": "2024-03-09"}, {"title": "Mushkin Essentials \u2013 DDR3 Desktop DRAM \u2013 8GB Memory Single Module DIMM \u2013 DDR3L-1600MHz (PC3L-12800) CL-11 \u2013 240-pin 1.35LV RAM \u2013 Low-Voltage \u2013 Non-ECC UDIMM \u2013 (992031)", "total_reviews": "168  ", "price": "", "image_url": "https://m.media-amazon.com/images/I/61V87TMXp1L._AC_UY218_.jpg", "scrape_date": "2024-03-09"}, {"title": "Timetec 16GB KIT(2x8GB) DDR4 2666MHz (DDR4-2666) PC4-21300 (PC4-2666V) Non-ECC Unbuffered 1.2V CL19 1Rx8 Single Rank 260 Pin SODIMM Laptop Notebook PC Computer Memory RAM Module Upgrade", "total_reviews": "2,614  ", "price": "32.99", "image_url": "https://m.media-amazon.com/images/I/71wWXQwxhuL._AC_UY218_.jpg", "scrape_date": "2024-03-09"}, {"title": "DDR3 1066MHz SODIMM 8GB Kit (2X4GB) 2Rx8 PC3-8500 PC3-8500S CL7 204 Pin 1.5V Non-ECC Unbuffered Laptop Memory RAM Modules", "total_reviews": "2,141  ", "price": "15.89", "image_url": "https://m.media-amazon.com/images/I/71Lfmq4yi8L._AC_UY218_.jpg", "scrape_date": "2024-03-09"}, {"title": "TECMIYO Ram 16GB Kit (4x4GB) DDR3 1333MHz 16GB PC3-10600/PC3 10600U Non ECC Unbuffered 1.5V CL9 2RX8 Dual Rank 240 Pin UDIMM Desktop Memory Ram Module (DDR3 4x4GB)", "total_reviews": "4,650  ", "price": "31.98", "image_url": "https://m.media-amazon.com/images/I/81IuP2n4hmL._AC_UY218_.jpg", "scrape_date": "2024-03-09"}, {"title": "16GB DDR4 3200MHz PC4-25600 CL22 1.2V 288-Pin Non-ECC UDIMM Desktop RAM Memory Module", "total_reviews": "67  ", "price": "31.49", "image_url": "https://m.media-amazon.com/images/I/51aCUwfF75L._AC_UY218_.jpg", "scrape_date": "2024-03-09"}, {"title": "A-Tech 128GB Kit (2x64GB) DDR4 2400MHz PC4-19200 ECC LRDIMM 4Rx4 Quad Rank 1.2V Load Reduced DIMM 288-Pin Server & Workstation RAM Memory Upgrade Modules (A-Tech Enterprise Series)", "total_reviews": "3  ", "price": "143.98", "image_url": "https://m.media-amazon.com/images/I/81JCbxk4BEL._AC_UY218_.jpg", "scrape_date": "2024-03-09"}, {"title": "1600MHZ DDR3 RAM 8GB ram XMP 1.2 (PC3-12800) 1.5V CL9 UDIMM PC Computer Desktop Memory Module Ram Upgrade Unbuffered Non-ECC Desktop Computer Memory", "total_reviews": "644  ", "price": "12.99", "image_url": "https://m.media-amazon.com/images/I/61dkijMJHLL._AC_UY218_.jpg", "scrape_date": "2024-03-09"}, {"title": "Patriot Memory Signature Premium DDR4 16GB (2x8GB) 3200MHz (PC4-25600) UDIMM Kit W/HEATSHIELD", "total_reviews": "644  ", "price": "40.99", "image_url": "https://m.media-amazon.com/images/I/81e+68VClAL._AC_UY218_.jpg", "scrape_date": "2024-03-09"}, {"title": "TEAMGROUP T-Force Vulcan Alpha DDR5 Ram 32GB Kit (2x16GB) 6000MHz (PC5-48000) CL38 Desktop Memory Module Ram (Black) AMD Optimized Memory - FLABD532G6000HC38ADC01", "total_reviews": "66  ", "price": "", "image_url": "https://m.media-amazon.com/images/I/81Wxc8nvo3L._AC_UY218_.jpg", "scrape_date": "2024-03-09"}, {"title": "HMA81GU6JJR8N-VK HYNIX 8GB 1RX8 PC4-2666V-U Memory Module (1X8GB)", "total_reviews": "28  ", "price": "28.22", "image_url": "https://m.media-amazon.com/images/I/51k5XhWcWPL._AC_UY218_.jpg", "scrape_date": "2024-03-09"}, {"title": "PC3-10600U 8GB Kit (2X4GB) DDR3 10600 1333MHz PC3-10600 4GB 2Rx8 240-pin Dimm CL9 1.5V Desktop RAM Memory Module", "total_reviews": "3,799  ", "price": "16.59", "image_url": "https://m.media-amazon.com/images/I/71zFU6qDgNL._AC_UY218_.jpg", "scrape_date": "2024-03-09"}, {"title": "16GB Kit (2x8GB) PC3-10600 DDR3 1333MHz Ram 16GB 2Rx8 PC3 10600U DDR3 1333 8GB Ram 240 Pin 1.5V CL9 1333 mhz DDR3 Desktop Memory Ram Module", "total_reviews": "901  ", "price": "26.99", "image_url": "https://m.media-amazon.com/images/I/71qj1VhZUJL._AC_UY218_.jpg", "scrape_date": "2024-03-09"}, {"title": "Samsung M323R2GA3BB0-CQK 16GB DDR5-4800 PC5-38400 4800MHz UDIMM Non-ECC UNBUFFERED Desktop RAM Memory Module", "total_reviews": "10  ", "price": "49.34", "image_url": "https://m.media-amazon.com/images/I/71KFKDsC+iL._AC_UY218_.jpg", "scrape_date": "2024-03-09"}, {"title": "CORSAIR VENGEANCE DDR5 RAM 64GB (2x32GB) 5600MHz CL40 Intel XMP iCUE Compatible Computer Memory - Black (CMK64GX5M2B5600C40)", "total_reviews": "2,461  ", "price": "189.99", "image_url": "https://m.media-amazon.com/images/I/71AV5PQu1yL._AC_UY218_.jpg", "scrape_date": "2024-03-09"}, {"title": "16GB (2x8GB) DDR4 17000U PC4 2133MHz UDIMM, DDR4-2133P PC4-17000 CL15 2Rx8 1.2V Non-ECC 288 Pin Desktop Memory Module Ram", "total_reviews": "88  ", "price": "30.99", "image_url": "https://m.media-amazon.com/images/I/71yinZzBD9L._AC_UY218_.jpg", "scrape_date": "2024-03-09"}, {"title": "Timetec 16GB KIT(2x8GB) Compatible for Apple DDR3L 1600MHz for Early/Mid/Late Mac Book Pro(2011-2012), iMac(2011-2015), Mac Mini(2011-2012) MAC RAM", "total_reviews": "9,490  ", "price": "18.99", "image_url": "https://m.media-amazon.com/images/I/71Ka4bpBOyL._AC_UY218_.jpg", "scrape_date": "2024-03-09"}, {"title": "Patriot Signature Line Series DDR4 16GB (1 x 16GB) 3200MHz (1 Rank Single-Sided Module)", "total_reviews": "49  ", "price": "33.99", "image_url": "https://m.media-amazon.com/images/I/81pvsZ6G2eL._AC_UY218_.jpg", "scrape_date": "2024-03-09"}]